gfworkflow/R.py
gfworkflow/__init__.py
gfworkflow/__main__.py
gfworkflow/base_resources.py
gfworkflow/core.py
gfworkflow/exceptions.py
gfworkflow/cli/__init__.py
gfworkflow/cli/_arg_parse.py
gfworkflow/cli/api.py
gfworkflow/res/VERSION
gfworkflow-0.1.0.dist-info/LICENSE
gfworkflow-0.1.0.dist-info/METADATA
gfworkflow-0.1.0.dist-info/WHEEL
gfworkflow-0.1.0.dist-info/entry_points.txt
gfworkflow-0.1.0.dist-info/top_level.txt
gfworkflow-0.1.0.dist-info/RECORD
