Metadata-Version: 2.1
Name: gfworkflow
Version: 0.1.0
Summary: A set of wrappers around git flow
Home-page: https://github.com/andersonbrands/gfworkflow
Author: Anderson Brandao
Author-email: anderson.brands@gmail.com
License: UNKNOWN
Platform: UNKNOWN
Classifier: Programming Language :: Python :: 3
Requires-Python: >=3.6
